constants/__init__.py
constants/constants.py
plutus_sdk-1.0.0.dist-info/METADATA
plutus_sdk-1.0.0.dist-info/WHEEL
plutus_sdk-1.0.0.dist-info/top_level.txt
plutus_sdk-1.0.0.dist-info/RECORD
