Metadata-Version: 2.4
Name: plutus-sdk
Version: 1.0.0
Summary: A Python SDK for Plutus API integration
Home-page: https://github.com/yourusername/sdk
Author: Your Name
Author-email: your.email@example.com
Classifier: Programming Language :: Python :: 3
Classifier: License :: OSI Approved :: MIT License
Classifier: Operating System :: OS Independent
Requires-Python: >=3.6
Requires-Dist: requests
Dynamic: author
Dynamic: author-email
Dynamic: classifier
Dynamic: description-content-type
Dynamic: home-page
Dynamic: requires-dist
Dynamic: requires-python
Dynamic: summary
